randorgdice/__init__.py
randorgdice-1.0.2.dist-info/LICENSE
randorgdice-1.0.2.dist-info/METADATA
randorgdice-1.0.2.dist-info/WHEEL
randorgdice-1.0.2.dist-info/top_level.txt
randorgdice-1.0.2.dist-info/RECORD
