Metadata-Version: 2.1
Name: randorgdice
Version: 1.0.2
Summary: Request integers from random.org
Home-page: https://github.com/albertocastronovo/randorgdice
Author: Alberto Castronovo
Author-email: alberto.castronovo@hotmail.it
License: UNKNOWN
Platform: UNKNOWN
Classifier: Programming Language :: Python :: 3
Classifier: License :: OSI Approved :: MIT License
Classifier: Operating System :: OS Independent
Requires-Python: >=3.6
